tinypublisher/__init__.py
tinypublisher/command.py
tinypublisher/builder/__init__.py
tinypublisher/builder/templates/container.xml
tinypublisher/builder/templates/navigation.xhtml
tinypublisher/builder/templates/package.opf
tinypublisher/builder/templates/page.css
tinypublisher/builder/templates/page.xhtml
tinypublisher/package/__init__.py
tinypublisher/reader/__init__.py
tinypublisher-0.3.2.dist-info/LICENSE.txt
tinypublisher-0.3.2.dist-info/METADATA
tinypublisher-0.3.2.dist-info/WHEEL
tinypublisher-0.3.2.dist-info/entry_points.txt
tinypublisher-0.3.2.dist-info/top_level.txt
tinypublisher-0.3.2.dist-info/RECORD
