Metadata-Version: 2.1
Name: tinypublisher
Version: 0.3.2
Summary: A tool to make a simple EPUB package.
Home-page: https://github.com/osmatsuda/tinypublisher
Author: Osamu Matsuda
Author-email: osmatsuda@gmail.com
License: UNKNOWN
Platform: UNKNOWN
Classifier: Development Status :: 4 - Beta
Classifier: Environment :: Console
Classifier: License :: OSI Approved :: MIT License
Classifier: Operating System :: OS Independent
Classifier: Programming Language :: Python :: 3
Classifier: Topic :: Documentation
Requires-Python: >=3.9
License-File: LICENSE.txt
Requires-Dist: mako (>=1.1)
Requires-Dist: python-magic (>=0.4)
